odoo/addons/multi_step_wizard/README.rst
odoo/addons/multi_step_wizard/__init__.py
odoo/addons/multi_step_wizard/__manifest__.py
odoo/addons/multi_step_wizard/i18n/ca.po
odoo/addons/multi_step_wizard/i18n/de.po
odoo/addons/multi_step_wizard/i18n/es.po
odoo/addons/multi_step_wizard/i18n/hr.po
odoo/addons/multi_step_wizard/i18n/it.po
odoo/addons/multi_step_wizard/i18n/multi_step_wizard.pot
odoo/addons/multi_step_wizard/i18n/nl.po
odoo/addons/multi_step_wizard/i18n/tr.po
odoo/addons/multi_step_wizard/i18n/zh_CN.po
odoo/addons/multi_step_wizard/models/__init__.py
odoo/addons/multi_step_wizard/models/multi_step_wizard.py
odoo/addons/multi_step_wizard/readme/CONTRIBUTORS.md
odoo/addons/multi_step_wizard/readme/DESCRIPTION.md
odoo/addons/multi_step_wizard/readme/USAGE.md
odoo/addons/multi_step_wizard/static/description/icon.png
odoo/addons/multi_step_wizard/static/description/index.html
odoo/addons/multi_step_wizard/tests/__init__.py
odoo/addons/multi_step_wizard/tests/common.py
odoo/addons/multi_step_wizard/tests/multi_step_wizard_test.py
odoo/addons/multi_step_wizard/tests/test_multi_step_wizard.py
odoo/addons/multi_step_wizard/views/multi_step_wizard_views.xml
odoo_addon_multi_step_wizard-18.0.1.0.0.3.dist-info/METADATA
odoo_addon_multi_step_wizard-18.0.1.0.0.3.dist-info/WHEEL
odoo_addon_multi_step_wizard-18.0.1.0.0.3.dist-info/top_level.txt
odoo_addon_multi_step_wizard-18.0.1.0.0.3.dist-info/RECORD
